codesnapper/__init__.py
codesnapper/app.py
codesnapper/codesnap.py
codesnapper/templates/index.html
codesnapper-0.1.7.dist-info/licenses/LICENSE
codesnapper-0.1.7.dist-info/METADATA
codesnapper-0.1.7.dist-info/WHEEL
codesnapper-0.1.7.dist-info/entry_points.txt
codesnapper-0.1.7.dist-info/top_level.txt
codesnapper-0.1.7.dist-info/RECORD
